README.md
setup.cfg
setup.py
jarboto/__init__.py
jarboto/jarboto.py
jarboto.egg-info/PKG-INFO
jarboto.egg-info/SOURCES.txt
jarboto.egg-info/dependency_links.txt
jarboto.egg-info/requires.txt
jarboto.egg-info/top_level.txt