Metadata-Version: 2.1
Name: jarboto
Version: 1.0.3
Summary: JARVICE container environment config wrapper for boto3
Home-page: https://github.com/nimbix/jarboto
Author: Nimbix, Inc.
Author-email: noreply@nimbix.net
License: LICENSE.txt
Download-URL: https://github.com/nimbix/jarboto/archive/v1.0.3.tar.gz
Keywords: s3,boto3,JARVICE
Platform: UNKNOWN
Classifier: Development Status :: 5 - Production/Stable
Classifier: Intended Audience :: Developers
Classifier: Topic :: Software Development :: Build Tools
Classifier: License :: OSI Approved :: BSD License
Classifier: Programming Language :: Python :: 2.7
Classifier: Programming Language :: Python :: 3
Classifier: Programming Language :: Python :: 3.4
Classifier: Programming Language :: Python :: 3.5
Classifier: Programming Language :: Python :: 3.6
Classifier: Programming Language :: Python :: 3.7
Classifier: Programming Language :: Python :: 3.8
